setup.cfg
setup.py
wefacts/__init__.py
wefacts/email_protocol.py
wefacts/fetcher.py
wefacts/geo.py
wefacts/parser.py
wefacts/searcher.py
wefacts/util.py
wefacts/wefacts.py
wefacts.egg-info/PKG-INFO
wefacts.egg-info/SOURCES.txt
wefacts.egg-info/dependency_links.txt
wefacts.egg-info/not-zip-safe
wefacts.egg-info/requires.txt
wefacts.egg-info/top_level.txt