Metadata-Version: 1.0
Name: wefacts
Version: 0.1.2
Summary: Weather Facts: get historical weather data.
Home-page: https://github.com/shawxiaozhang/wefacts
Author: Xiao Zhang
Author-email: shawxiaozhang@gmail.com
License: MIT
Platform: UNKNOWN
